{
  "type": "File",
  "start": 0,
  "end": 481,
  "loc": {
    "start": {
      "line": 1,
      "column": 0
    },
    "end": {
      "line": 15,
      "column": 35
    }
  },
  "program": {
    "type": "Program",
    "start": 0,
    "end": 481,
    "loc": {
      "start": {
        "line": 1,
        "column": 0
      },
      "end": {
        "line": 15,
        "column": 35
      }
    },
    "sourceType": "module",
    "body": [
      {
        "type": "ImportDeclaration",
        "start": 0,
        "end": 32,
        "loc": {
          "start": {
            "line": 1,
            "column": 0
          },
          "end": {
            "line": 1,
            "column": 32
          }
        },
        "specifiers": [
          {
            "type": "ImportDefaultSpecifier",
            "start": 7,
            "end": 15,
            "loc": {
              "start": {
                "line": 1,
                "column": 7
              },
              "end": {
                "line": 1,
                "column": 15
              }
            },
            "local": {
              "type": "Identifier",
              "start": 7,
              "end": 15,
              "loc": {
                "start": {
                  "line": 1,
                  "column": 7
                },
                "end": {
                  "line": 1,
                  "column": 15
                },
                "identifierName": "isObject"
              },
              "name": "isObject"
            }
          }
        ],
        "source": {
          "type": "StringLiteral",
          "start": 21,
          "end": 31,
          "loc": {
            "start": {
              "line": 1,
              "column": 21
            },
            "end": {
              "line": 1,
              "column": 31
            }
          },
          "extra": {
            "rawValue": "./object",
            "raw": "'./object'"
          },
          "value": "./object"
        }
      },
      {
        "type": "ImportDeclaration",
        "start": 33,
        "end": 69,
        "loc": {
          "start": {
            "line": 2,
            "column": 0
          },
          "end": {
            "line": 2,
            "column": 36
          }
        },
        "specifiers": [
          {
            "type": "ImportDefaultSpecifier",
            "start": 40,
            "end": 50,
            "loc": {
              "start": {
                "line": 2,
                "column": 7
              },
              "end": {
                "line": 2,
                "column": 17
              }
            },
            "local": {
              "type": "Identifier",
              "start": 40,
              "end": 50,
              "loc": {
                "start": {
                  "line": 2,
                  "column": 7
                },
                "end": {
                  "line": 2,
                  "column": 17
                },
                "identifierName": "isFunction"
              },
              "name": "isFunction"
            }
          }
        ],
        "source": {
          "type": "StringLiteral",
          "start": 56,
          "end": 68,
          "loc": {
            "start": {
              "line": 2,
              "column": 23
            },
            "end": {
              "line": 2,
              "column": 35
            }
          },
          "extra": {
            "rawValue": "./function",
            "raw": "'./function'"
          },
          "value": "./function"
        },
        "trailingComments": [
          {
            "type": "CommentBlock",
            "value": "*\n * Checks if `test` is Promise.\n *\n * @param {*} test The value to check.\n * @returns {boolean} Returns `true` if `test` is Promise, else `false`.\n * @example\n *\n *      isPromise({}) // => false\n *      isPromise(Promise.resolve()) // => true\n ",
            "start": 70,
            "end": 321,
            "loc": {
              "start": {
                "line": 3,
                "column": 0
              },
              "end": {
                "line": 12,
                "column": 3
              }
            }
          }
        ]
      },
      {
        "type": "ExportNamedDeclaration",
        "start": 322,
        "end": 419,
        "loc": {
          "start": {
            "line": 13,
            "column": 0
          },
          "end": {
            "line": 13,
            "column": 97
          }
        },
        "specifiers": [],
        "source": null,
        "declaration": {
          "type": "VariableDeclaration",
          "start": 329,
          "end": 419,
          "loc": {
            "start": {
              "line": 13,
              "column": 7
            },
            "end": {
              "line": 13,
              "column": 97
            }
          },
          "declarations": [
            {
              "type": "VariableDeclarator",
              "start": 335,
              "end": 418,
              "loc": {
                "start": {
                  "line": 13,
                  "column": 13
                },
                "end": {
                  "line": 13,
                  "column": 96
                }
              },
              "id": {
                "type": "Identifier",
                "start": 335,
                "end": 344,
                "loc": {
                  "start": {
                    "line": 13,
                    "column": 13
                  },
                  "end": {
                    "line": 13,
                    "column": 22
                  },
                  "identifierName": "isPromise"
                },
                "name": "isPromise",
                "leadingComments": null
              },
              "init": {
                "type": "ArrowFunctionExpression",
                "start": 347,
                "end": 418,
                "loc": {
                  "start": {
                    "line": 13,
                    "column": 25
                  },
                  "end": {
                    "line": 13,
                    "column": 96
                  }
                },
                "id": {
                  "type": "Identifier",
                  "start": 335,
                  "end": 344,
                  "loc": {
                    "start": {
                      "line": 13,
                      "column": 13
                    },
                    "end": {
                      "line": 13,
                      "column": 22
                    },
                    "identifierName": "isPromise"
                  },
                  "name": "isPromise",
                  "leadingComments": null
                },
                "generator": false,
                "expression": true,
                "async": false,
                "params": [
                  {
                    "type": "Identifier",
                    "start": 348,
                    "end": 352,
                    "loc": {
                      "start": {
                        "line": 13,
                        "column": 26
                      },
                      "end": {
                        "line": 13,
                        "column": 30
                      },
                      "identifierName": "test"
                    },
                    "name": "test"
                  }
                ],
                "body": {
                  "type": "LogicalExpression",
                  "start": 357,
                  "end": 418,
                  "loc": {
                    "start": {
                      "line": 13,
                      "column": 35
                    },
                    "end": {
                      "line": 13,
                      "column": 96
                    }
                  },
                  "left": {
                    "type": "LogicalExpression",
                    "start": 358,
                    "end": 392,
                    "loc": {
                      "start": {
                        "line": 13,
                        "column": 36
                      },
                      "end": {
                        "line": 13,
                        "column": 70
                      }
                    },
                    "left": {
                      "type": "CallExpression",
                      "start": 358,
                      "end": 372,
                      "loc": {
                        "start": {
                          "line": 13,
                          "column": 36
                        },
                        "end": {
                          "line": 13,
                          "column": 50
                        }
                      },
                      "callee": {
                        "type": "Identifier",
                        "start": 358,
                        "end": 366,
                        "loc": {
                          "start": {
                            "line": 13,
                            "column": 36
                          },
                          "end": {
                            "line": 13,
                            "column": 44
                          },
                          "identifierName": "isObject"
                        },
                        "name": "isObject"
                      },
                      "arguments": [
                        {
                          "type": "Identifier",
                          "start": 367,
                          "end": 371,
                          "loc": {
                            "start": {
                              "line": 13,
                              "column": 45
                            },
                            "end": {
                              "line": 13,
                              "column": 49
                            },
                            "identifierName": "test"
                          },
                          "name": "test"
                        }
                      ]
                    },
                    "operator": "||",
                    "right": {
                      "type": "CallExpression",
                      "start": 376,
                      "end": 392,
                      "loc": {
                        "start": {
                          "line": 13,
                          "column": 54
                        },
                        "end": {
                          "line": 13,
                          "column": 70
                        }
                      },
                      "callee": {
                        "type": "Identifier",
                        "start": 376,
                        "end": 386,
                        "loc": {
                          "start": {
                            "line": 13,
                            "column": 54
                          },
                          "end": {
                            "line": 13,
                            "column": 64
                          },
                          "identifierName": "isFunction"
                        },
                        "name": "isFunction"
                      },
                      "arguments": [
                        {
                          "type": "Identifier",
                          "start": 387,
                          "end": 391,
                          "loc": {
                            "start": {
                              "line": 13,
                              "column": 65
                            },
                            "end": {
                              "line": 13,
                              "column": 69
                            },
                            "identifierName": "test"
                          },
                          "name": "test"
                        }
                      ]
                    },
                    "extra": {
                      "parenthesized": true,
                      "parenStart": 357
                    }
                  },
                  "operator": "&&",
                  "right": {
                    "type": "CallExpression",
                    "start": 397,
                    "end": 418,
                    "loc": {
                      "start": {
                        "line": 13,
                        "column": 75
                      },
                      "end": {
                        "line": 13,
                        "column": 96
                      }
                    },
                    "callee": {
                      "type": "Identifier",
                      "start": 397,
                      "end": 407,
                      "loc": {
                        "start": {
                          "line": 13,
                          "column": 75
                        },
                        "end": {
                          "line": 13,
                          "column": 85
                        },
                        "identifierName": "isFunction"
                      },
                      "name": "isFunction"
                    },
                    "arguments": [
                      {
                        "type": "MemberExpression",
                        "start": 408,
                        "end": 417,
                        "loc": {
                          "start": {
                            "line": 13,
                            "column": 86
                          },
                          "end": {
                            "line": 13,
                            "column": 95
                          }
                        },
                        "object": {
                          "type": "Identifier",
                          "start": 408,
                          "end": 412,
                          "loc": {
                            "start": {
                              "line": 13,
                              "column": 86
                            },
                            "end": {
                              "line": 13,
                              "column": 90
                            },
                            "identifierName": "test"
                          },
                          "name": "test"
                        },
                        "property": {
                          "type": "Identifier",
                          "start": 413,
                          "end": 417,
                          "loc": {
                            "start": {
                              "line": 13,
                              "column": 91
                            },
                            "end": {
                              "line": 13,
                              "column": 95
                            },
                            "identifierName": "then"
                          },
                          "name": "then"
                        },
                        "computed": false
                      }
                    ]
                  }
                }
              },
              "leadingComments": null
            }
          ],
          "kind": "const",
          "leadingComments": [
            {
              "type": "CommentBlock",
              "value": "*\n * Checks if `test` is Promise.\n *\n * @param {*} test The value to check.\n * @returns {boolean} Returns `true` if `test` is Promise, else `false`.\n * @example\n *\n *      isPromise({}) // => false\n *      isPromise(Promise.resolve()) // => true\n ",
              "start": 70,
              "end": 321,
              "loc": {
                "start": {
                  "line": 3,
                  "column": 0
                },
                "end": {
                  "line": 12,
                  "column": 3
                }
              }
            }
          ],
          "trailingComments": []
        },
        "leadingComments": [
          {
            "type": "CommentBlock",
            "value": "*\n * Checks if `test` is Promise.\n *\n * @param {*} test The value to check.\n * @returns {boolean} Returns `true` if `test` is Promise, else `false`.\n * @example\n *\n *      isPromise({}) // => false\n *      isPromise(Promise.resolve()) // => true\n ",
            "start": 70,
            "end": 321,
            "loc": {
              "start": {
                "line": 3,
                "column": 0
              },
              "end": {
                "line": 12,
                "column": 3
              }
            }
          }
        ]
      },
      {
        "type": "ExportDefaultDeclaration",
        "start": 420,
        "end": 445,
        "loc": {
          "start": {
            "line": 14,
            "column": 0
          },
          "end": {
            "line": 14,
            "column": 25
          }
        },
        "declaration": {
          "type": "Identifier",
          "start": 435,
          "end": 444,
          "loc": {
            "start": {
              "line": 14,
              "column": 15
            },
            "end": {
              "line": 14,
              "column": 24
            },
            "identifierName": "isPromise"
          },
          "name": "isPromise",
          "leadingComments": [],
          "trailingComments": [
            {
              "type": "CommentLine",
              "value": "# sourceMappingURL=promise.js.map",
              "start": 446,
              "end": 481,
              "loc": {
                "start": {
                  "line": 15,
                  "column": 0
                },
                "end": {
                  "line": 15,
                  "column": 35
                }
              }
            }
          ]
        },
        "trailingComments": [
          {
            "type": "CommentLine",
            "value": "# sourceMappingURL=promise.js.map",
            "start": 446,
            "end": 481,
            "loc": {
              "start": {
                "line": 15,
                "column": 0
              },
              "end": {
                "line": 15,
                "column": 35
              }
            }
          }
        ]
      }
    ],
    "directives": []
  },
  "comments": [
    {
      "type": "CommentBlock",
      "value": "*\n * Checks if `test` is Promise.\n *\n * @param {*} test The value to check.\n * @returns {boolean} Returns `true` if `test` is Promise, else `false`.\n * @example\n *\n *      isPromise({}) // => false\n *      isPromise(Promise.resolve()) // => true\n ",
      "start": 70,
      "end": 321,
      "loc": {
        "start": {
          "line": 3,
          "column": 0
        },
        "end": {
          "line": 12,
          "column": 3
        }
      }
    },
    {
      "type": "CommentLine",
      "value": "# sourceMappingURL=promise.js.map",
      "start": 446,
      "end": 481,
      "loc": {
        "start": {
          "line": 15,
          "column": 0
        },
        "end": {
          "line": 15,
          "column": 35
        }
      }
    }
  ],
  "tokens": [
    {
      "type": {
        "label": "import",
        "keyword": "import",
        "beforeExpr": false,
        "startsExpr": true,
        "rightAssociative": false,
        "isLoop": false,
        "isAssign": false,
        "prefix": false,
        "postfix": false,
        "binop": null,
        "updateContext": null
      },
      "value": "import",
      "start": 0,
      "end": 6,
      "loc": {
        "start": {
          "line": 1,
          "column": 0
        },
        "end": {
          "line": 1,
          "column": 6
        }
      }
    },
    {
      "type": {
        "label": "name",
        "beforeExpr": false,
        "startsExpr": true,
        "rightAssociative": false,
        "isLoop": false,
        "isAssign": false,
        "prefix": false,
        "postfix": false,
        "binop": null
      },
      "value": "isObject",
      "start": 7,
      "end": 15,
      "loc": {
        "start": {
          "line": 1,
          "column": 7
        },
        "end": {
          "line": 1,
          "column": 15
        }
      }
    },
    {
      "type": {
        "label": "name",
        "beforeExpr": false,
        "startsExpr": true,
        "rightAssociative": false,
        "isLoop": false,
        "isAssign": false,
        "prefix": false,
        "postfix": false,
        "binop": null
      },
      "value": "from",
      "start": 16,
      "end": 20,
      "loc": {
        "start": {
          "line": 1,
          "column": 16
        },
        "end": {
          "line": 1,
          "column": 20
        }
      }
    },
    {
      "type": {
        "label": "string",
        "beforeExpr": false,
        "startsExpr": true,
        "rightAssociative": false,
        "isLoop": false,
        "isAssign": false,
        "prefix": false,
        "postfix": false,
        "binop": null,
        "updateContext": null
      },
      "value": "./object",
      "start": 21,
      "end": 31,
      "loc": {
        "start": {
          "line": 1,
          "column": 21
        },
        "end": {
          "line": 1,
          "column": 31
        }
      }
    },
    {
      "type": {
        "label": ";",
        "beforeExpr": true,
        "startsExpr": false,
        "rightAssociative": false,
        "isLoop": false,
        "isAssign": false,
        "prefix": false,
        "postfix": false,
        "binop": null,
        "updateContext": null
      },
      "start": 31,
      "end": 32,
      "loc": {
        "start": {
          "line": 1,
          "column": 31
        },
        "end": {
          "line": 1,
          "column": 32
        }
      }
    },
    {
      "type": {
        "label": "import",
        "keyword": "import",
        "beforeExpr": false,
        "startsExpr": true,
        "rightAssociative": false,
        "isLoop": false,
        "isAssign": false,
        "prefix": false,
        "postfix": false,
        "binop": null,
        "updateContext": null
      },
      "value": "import",
      "start": 33,
      "end": 39,
      "loc": {
        "start": {
          "line": 2,
          "column": 0
        },
        "end": {
          "line": 2,
          "column": 6
        }
      }
    },
    {
      "type": {
        "label": "name",
        "beforeExpr": false,
        "startsExpr": true,
        "rightAssociative": false,
        "isLoop": false,
        "isAssign": false,
        "prefix": false,
        "postfix": false,
        "binop": null
      },
      "value": "isFunction",
      "start": 40,
      "end": 50,
      "loc": {
        "start": {
          "line": 2,
          "column": 7
        },
        "end": {
          "line": 2,
          "column": 17
        }
      }
    },
    {
      "type": {
        "label": "name",
        "beforeExpr": false,
        "startsExpr": true,
        "rightAssociative": false,
        "isLoop": false,
        "isAssign": false,
        "prefix": false,
        "postfix": false,
        "binop": null
      },
      "value": "from",
      "start": 51,
      "end": 55,
      "loc": {
        "start": {
          "line": 2,
          "column": 18
        },
        "end": {
          "line": 2,
          "column": 22
        }
      }
    },
    {
      "type": {
        "label": "string",
        "beforeExpr": false,
        "startsExpr": true,
        "rightAssociative": false,
        "isLoop": false,
        "isAssign": false,
        "prefix": false,
        "postfix": false,
        "binop": null,
        "updateContext": null
      },
      "value": "./function",
      "start": 56,
      "end": 68,
      "loc": {
        "start": {
          "line": 2,
          "column": 23
        },
        "end": {
          "line": 2,
          "column": 35
        }
      }
    },
    {
      "type": {
        "label": ";",
        "beforeExpr": true,
        "startsExpr": false,
        "rightAssociative": false,
        "isLoop": false,
        "isAssign": false,
        "prefix": false,
        "postfix": false,
        "binop": null,
        "updateContext": null
      },
      "start": 68,
      "end": 69,
      "loc": {
        "start": {
          "line": 2,
          "column": 35
        },
        "end": {
          "line": 2,
          "column": 36
        }
      }
    },
    {
      "type": "CommentBlock",
      "value": "*\n * Checks if `test` is Promise.\n *\n * @param {*} test The value to check.\n * @returns {boolean} Returns `true` if `test` is Promise, else `false`.\n * @example\n *\n *      isPromise({}) // => false\n *      isPromise(Promise.resolve()) // => true\n ",
      "start": 70,
      "end": 321,
      "loc": {
        "start": {
          "line": 3,
          "column": 0
        },
        "end": {
          "line": 12,
          "column": 3
        }
      }
    },
    {
      "type": {
        "label": "export",
        "keyword": "export",
        "beforeExpr": false,
        "startsExpr": false,
        "rightAssociative": false,
        "isLoop": false,
        "isAssign": false,
        "prefix": false,
        "postfix": false,
        "binop": null,
        "updateContext": null
      },
      "value": "export",
      "start": 322,
      "end": 328,
      "loc": {
        "start": {
          "line": 13,
          "column": 0
        },
        "end": {
          "line": 13,
          "column": 6
        }
      }
    },
    {
      "type": {
        "label": "const",
        "keyword": "const",
        "beforeExpr": false,
        "startsExpr": false,
        "rightAssociative": false,
        "isLoop": false,
        "isAssign": false,
        "prefix": false,
        "postfix": false,
        "binop": null,
        "updateContext": null
      },
      "value": "const",
      "start": 329,
      "end": 334,
      "loc": {
        "start": {
          "line": 13,
          "column": 7
        },
        "end": {
          "line": 13,
          "column": 12
        }
      }
    },
    {
      "type": {
        "label": "name",
        "beforeExpr": false,
        "startsExpr": true,
        "rightAssociative": false,
        "isLoop": false,
        "isAssign": false,
        "prefix": false,
        "postfix": false,
        "binop": null
      },
      "value": "isPromise",
      "start": 335,
      "end": 344,
      "loc": {
        "start": {
          "line": 13,
          "column": 13
        },
        "end": {
          "line": 13,
          "column": 22
        }
      }
    },
    {
      "type": {
        "label": "=",
        "beforeExpr": true,
        "startsExpr": false,
        "rightAssociative": false,
        "isLoop": false,
        "isAssign": true,
        "prefix": false,
        "postfix": false,
        "binop": null,
        "updateContext": null
      },
      "value": "=",
      "start": 345,
      "end": 346,
      "loc": {
        "start": {
          "line": 13,
          "column": 23
        },
        "end": {
          "line": 13,
          "column": 24
        }
      }
    },
    {
      "type": {
        "label": "(",
        "beforeExpr": true,
        "startsExpr": true,
        "rightAssociative": false,
        "isLoop": false,
        "isAssign": false,
        "prefix": false,
        "postfix": false,
        "binop": null
      },
      "start": 347,
      "end": 348,
      "loc": {
        "start": {
          "line": 13,
          "column": 25
        },
        "end": {
          "line": 13,
          "column": 26
        }
      }
    },
    {
      "type": {
        "label": "name",
        "beforeExpr": false,
        "startsExpr": true,
        "rightAssociative": false,
        "isLoop": false,
        "isAssign": false,
        "prefix": false,
        "postfix": false,
        "binop": null
      },
      "value": "test",
      "start": 348,
      "end": 352,
      "loc": {
        "start": {
          "line": 13,
          "column": 26
        },
        "end": {
          "line": 13,
          "column": 30
        }
      }
    },
    {
      "type": {
        "label": ")",
        "beforeExpr": false,
        "startsExpr": false,
        "rightAssociative": false,
        "isLoop": false,
        "isAssign": false,
        "prefix": false,
        "postfix": false,
        "binop": null
      },
      "start": 352,
      "end": 353,
      "loc": {
        "start": {
          "line": 13,
          "column": 30
        },
        "end": {
          "line": 13,
          "column": 31
        }
      }
    },
    {
      "type": {
        "label": "=>",
        "beforeExpr": true,
        "startsExpr": false,
        "rightAssociative": false,
        "isLoop": false,
        "isAssign": false,
        "prefix": false,
        "postfix": false,
        "binop": null,
        "updateContext": null
      },
      "start": 354,
      "end": 356,
      "loc": {
        "start": {
          "line": 13,
          "column": 32
        },
        "end": {
          "line": 13,
          "column": 34
        }
      }
    },
    {
      "type": {
        "label": "(",
        "beforeExpr": true,
        "startsExpr": true,
        "rightAssociative": false,
        "isLoop": false,
        "isAssign": false,
        "prefix": false,
        "postfix": false,
        "binop": null
      },
      "start": 357,
      "end": 358,
      "loc": {
        "start": {
          "line": 13,
          "column": 35
        },
        "end": {
          "line": 13,
          "column": 36
        }
      }
    },
    {
      "type": {
        "label": "name",
        "beforeExpr": false,
        "startsExpr": true,
        "rightAssociative": false,
        "isLoop": false,
        "isAssign": false,
        "prefix": false,
        "postfix": false,
        "binop": null
      },
      "value": "isObject",
      "start": 358,
      "end": 366,
      "loc": {
        "start": {
          "line": 13,
          "column": 36
        },
        "end": {
          "line": 13,
          "column": 44
        }
      }
    },
    {
      "type": {
        "label": "(",
        "beforeExpr": true,
        "startsExpr": true,
        "rightAssociative": false,
        "isLoop": false,
        "isAssign": false,
        "prefix": false,
        "postfix": false,
        "binop": null
      },
      "start": 366,
      "end": 367,
      "loc": {
        "start": {
          "line": 13,
          "column": 44
        },
        "end": {
          "line": 13,
          "column": 45
        }
      }
    },
    {
      "type": {
        "label": "name",
        "beforeExpr": false,
        "startsExpr": true,
        "rightAssociative": false,
        "isLoop": false,
        "isAssign": false,
        "prefix": false,
        "postfix": false,
        "binop": null
      },
      "value": "test",
      "start": 367,
      "end": 371,
      "loc": {
        "start": {
          "line": 13,
          "column": 45
        },
        "end": {
          "line": 13,
          "column": 49
        }
      }
    },
    {
      "type": {
        "label": ")",
        "beforeExpr": false,
        "startsExpr": false,
        "rightAssociative": false,
        "isLoop": false,
        "isAssign": false,
        "prefix": false,
        "postfix": false,
        "binop": null
      },
      "start": 371,
      "end": 372,
      "loc": {
        "start": {
          "line": 13,
          "column": 49
        },
        "end": {
          "line": 13,
          "column": 50
        }
      }
    },
    {
      "type": {
        "label": "||",
        "beforeExpr": true,
        "startsExpr": false,
        "rightAssociative": false,
        "isLoop": false,
        "isAssign": false,
        "prefix": false,
        "postfix": false,
        "binop": 1,
        "updateContext": null
      },
      "value": "||",
      "start": 373,
      "end": 375,
      "loc": {
        "start": {
          "line": 13,
          "column": 51
        },
        "end": {
          "line": 13,
          "column": 53
        }
      }
    },
    {
      "type": {
        "label": "name",
        "beforeExpr": false,
        "startsExpr": true,
        "rightAssociative": false,
        "isLoop": false,
        "isAssign": false,
        "prefix": false,
        "postfix": false,
        "binop": null
      },
      "value": "isFunction",
      "start": 376,
      "end": 386,
      "loc": {
        "start": {
          "line": 13,
          "column": 54
        },
        "end": {
          "line": 13,
          "column": 64
        }
      }
    },
    {
      "type": {
        "label": "(",
        "beforeExpr": true,
        "startsExpr": true,
        "rightAssociative": false,
        "isLoop": false,
        "isAssign": false,
        "prefix": false,
        "postfix": false,
        "binop": null
      },
      "start": 386,
      "end": 387,
      "loc": {
        "start": {
          "line": 13,
          "column": 64
        },
        "end": {
          "line": 13,
          "column": 65
        }
      }
    },
    {
      "type": {
        "label": "name",
        "beforeExpr": false,
        "startsExpr": true,
        "rightAssociative": false,
        "isLoop": false,
        "isAssign": false,
        "prefix": false,
        "postfix": false,
        "binop": null
      },
      "value": "test",
      "start": 387,
      "end": 391,
      "loc": {
        "start": {
          "line": 13,
          "column": 65
        },
        "end": {
          "line": 13,
          "column": 69
        }
      }
    },
    {
      "type": {
        "label": ")",
        "beforeExpr": false,
        "startsExpr": false,
        "rightAssociative": false,
        "isLoop": false,
        "isAssign": false,
        "prefix": false,
        "postfix": false,
        "binop": null
      },
      "start": 391,
      "end": 392,
      "loc": {
        "start": {
          "line": 13,
          "column": 69
        },
        "end": {
          "line": 13,
          "column": 70
        }
      }
    },
    {
      "type": {
        "label": ")",
        "beforeExpr": false,
        "startsExpr": false,
        "rightAssociative": false,
        "isLoop": false,
        "isAssign": false,
        "prefix": false,
        "postfix": false,
        "binop": null
      },
      "start": 392,
      "end": 393,
      "loc": {
        "start": {
          "line": 13,
          "column": 70
        },
        "end": {
          "line": 13,
          "column": 71
        }
      }
    },
    {
      "type": {
        "label": "&&",
        "beforeExpr": true,
        "startsExpr": false,
        "rightAssociative": false,
        "isLoop": false,
        "isAssign": false,
        "prefix": false,
        "postfix": false,
        "binop": 2,
        "updateContext": null
      },
      "value": "&&",
      "start": 394,
      "end": 396,
      "loc": {
        "start": {
          "line": 13,
          "column": 72
        },
        "end": {
          "line": 13,
          "column": 74
        }
      }
    },
    {
      "type": {
        "label": "name",
        "beforeExpr": false,
        "startsExpr": true,
        "rightAssociative": false,
        "isLoop": false,
        "isAssign": false,
        "prefix": false,
        "postfix": false,
        "binop": null
      },
      "value": "isFunction",
      "start": 397,
      "end": 407,
      "loc": {
        "start": {
          "line": 13,
          "column": 75
        },
        "end": {
          "line": 13,
          "column": 85
        }
      }
    },
    {
      "type": {
        "label": "(",
        "beforeExpr": true,
        "startsExpr": true,
        "rightAssociative": false,
        "isLoop": false,
        "isAssign": false,
        "prefix": false,
        "postfix": false,
        "binop": null
      },
      "start": 407,
      "end": 408,
      "loc": {
        "start": {
          "line": 13,
          "column": 85
        },
        "end": {
          "line": 13,
          "column": 86
        }
      }
    },
    {
      "type": {
        "label": "name",
        "beforeExpr": false,
        "startsExpr": true,
        "rightAssociative": false,
        "isLoop": false,
        "isAssign": false,
        "prefix": false,
        "postfix": false,
        "binop": null
      },
      "value": "test",
      "start": 408,
      "end": 412,
      "loc": {
        "start": {
          "line": 13,
          "column": 86
        },
        "end": {
          "line": 13,
          "column": 90
        }
      }
    },
    {
      "type": {
        "label": ".",
        "beforeExpr": false,
        "startsExpr": false,
        "rightAssociative": false,
        "isLoop": false,
        "isAssign": false,
        "prefix": false,
        "postfix": false,
        "binop": null,
        "updateContext": null
      },
      "start": 412,
      "end": 413,
      "loc": {
        "start": {
          "line": 13,
          "column": 90
        },
        "end": {
          "line": 13,
          "column": 91
        }
      }
    },
    {
      "type": {
        "label": "name",
        "beforeExpr": false,
        "startsExpr": true,
        "rightAssociative": false,
        "isLoop": false,
        "isAssign": false,
        "prefix": false,
        "postfix": false,
        "binop": null
      },
      "value": "then",
      "start": 413,
      "end": 417,
      "loc": {
        "start": {
          "line": 13,
          "column": 91
        },
        "end": {
          "line": 13,
          "column": 95
        }
      }
    },
    {
      "type": {
        "label": ")",
        "beforeExpr": false,
        "startsExpr": false,
        "rightAssociative": false,
        "isLoop": false,
        "isAssign": false,
        "prefix": false,
        "postfix": false,
        "binop": null
      },
      "start": 417,
      "end": 418,
      "loc": {
        "start": {
          "line": 13,
          "column": 95
        },
        "end": {
          "line": 13,
          "column": 96
        }
      }
    },
    {
      "type": {
        "label": ";",
        "beforeExpr": true,
        "startsExpr": false,
        "rightAssociative": false,
        "isLoop": false,
        "isAssign": false,
        "prefix": false,
        "postfix": false,
        "binop": null,
        "updateContext": null
      },
      "start": 418,
      "end": 419,
      "loc": {
        "start": {
          "line": 13,
          "column": 96
        },
        "end": {
          "line": 13,
          "column": 97
        }
      }
    },
    {
      "type": {
        "label": "export",
        "keyword": "export",
        "beforeExpr": false,
        "startsExpr": false,
        "rightAssociative": false,
        "isLoop": false,
        "isAssign": false,
        "prefix": false,
        "postfix": false,
        "binop": null,
        "updateContext": null
      },
      "value": "export",
      "start": 420,
      "end": 426,
      "loc": {
        "start": {
          "line": 14,
          "column": 0
        },
        "end": {
          "line": 14,
          "column": 6
        }
      }
    },
    {
      "type": {
        "label": "default",
        "keyword": "default",
        "beforeExpr": true,
        "startsExpr": false,
        "rightAssociative": false,
        "isLoop": false,
        "isAssign": false,
        "prefix": false,
        "postfix": false,
        "binop": null,
        "updateContext": null
      },
      "value": "default",
      "start": 427,
      "end": 434,
      "loc": {
        "start": {
          "line": 14,
          "column": 7
        },
        "end": {
          "line": 14,
          "column": 14
        }
      }
    },
    {
      "type": {
        "label": "name",
        "beforeExpr": false,
        "startsExpr": true,
        "rightAssociative": false,
        "isLoop": false,
        "isAssign": false,
        "prefix": false,
        "postfix": false,
        "binop": null
      },
      "value": "isPromise",
      "start": 435,
      "end": 444,
      "loc": {
        "start": {
          "line": 14,
          "column": 15
        },
        "end": {
          "line": 14,
          "column": 24
        }
      }
    },
    {
      "type": {
        "label": ";",
        "beforeExpr": true,
        "startsExpr": false,
        "rightAssociative": false,
        "isLoop": false,
        "isAssign": false,
        "prefix": false,
        "postfix": false,
        "binop": null,
        "updateContext": null
      },
      "start": 444,
      "end": 445,
      "loc": {
        "start": {
          "line": 14,
          "column": 24
        },
        "end": {
          "line": 14,
          "column": 25
        }
      }
    },
    {
      "type": "CommentLine",
      "value": "# sourceMappingURL=promise.js.map",
      "start": 446,
      "end": 481,
      "loc": {
        "start": {
          "line": 15,
          "column": 0
        },
        "end": {
          "line": 15,
          "column": 35
        }
      }
    },
    {
      "type": {
        "label": "eof",
        "beforeExpr": false,
        "startsExpr": false,
        "rightAssociative": false,
        "isLoop": false,
        "isAssign": false,
        "prefix": false,
        "postfix": false,
        "binop": null,
        "updateContext": null
      },
      "start": 481,
      "end": 481,
      "loc": {
        "start": {
          "line": 15,
          "column": 35
        },
        "end": {
          "line": 15,
          "column": 35
        }
      }
    }
  ]
}